span_ncnn_py-1.2.0.dist-info/METADATA
span_ncnn_py-1.2.0.dist-info/WHEEL
span_ncnn_py-1.2.0.dist-info/licenses/LICENSE
span_ncnn_py/__init__.py
span_ncnn_py/custom_models/2xHFA2kSPAN_27k.bin
span_ncnn_py/custom_models/2xHFA2kSPAN_27k.param
span_ncnn_py/custom_models/2x_span_anime_pretrain.bin
span_ncnn_py/custom_models/2x_span_anime_pretrain.param
span_ncnn_py/custom_models/4xSPANkendata.bin
span_ncnn_py/custom_models/4xSPANkendata.param
span_ncnn_py/custom_models/ClearReality4x.bin
span_ncnn_py/custom_models/ClearReality4x.param
span_ncnn_py/models/2xHFA2kSPAN_27k.bin
span_ncnn_py/models/2xHFA2kSPAN_27k.param
span_ncnn_py/models/4xSPANkendata.bin
span_ncnn_py/models/4xSPANkendata.param
span_ncnn_py/models/ClearReality4x.bin
span_ncnn_py/models/ClearReality4x.param
span_ncnn_py/models/spanx2_ch48.bin
span_ncnn_py/models/spanx2_ch48.param
span_ncnn_py/models/spanx2_ch52.bin
span_ncnn_py/models/spanx2_ch52.param
span_ncnn_py/models/spanx4_ch48.bin
span_ncnn_py/models/spanx4_ch48.param
span_ncnn_py/models/spanx4_ch52.bin
span_ncnn_py/models/spanx4_ch52.param
span_ncnn_py/span_ncnn_vulkan.py
span_ncnn_py-1.2.0.dist-info/RECORD
